<game>
<id>400489722</id>
<date>7:30 PM ET, February 25, 2014</date>
<team>
<name>Chicago Bulls</name>
<player>
<name>Carlos Boozer</name>
<pos>PF</pos>
<start>true</start>
<min>28</min>
<fgm>8</fgm>
<fga>14</fga>
<tpm>0</tpm>
<tpa>0</tpa>
<ftm>1</ftm>
<fta>2</fta>
<oreb>1</oreb>
<dreb>10</dreb>
<reb>11</reb>
<ast>1</ast>
<stl>1</stl>
<blk>2</blk>
<to>4</to>
<pf>2</pf>
<pam>+2</pam>
<pts>17</pts>
<dnp>false</dnp>
</player>
<player>
<name>Mike Dunleavy</name>
<pos>SF</pos>
<start>true</start>
<min>48</min>
<fgm>6</fgm>
<fga>15</fga>
<tpm>4</tpm>
<tpa>9</tpa>
<ftm>6</ftm>
<fta>6</fta>
<oreb>4</oreb>
<dreb>4</dreb>
<reb>8</reb>
<ast>4</ast>
<stl>0</stl>
<blk>0</blk>
<to>2</to>
<pf>4</pf>
<pam>+7</pam>
<pts>22</pts>
<dnp>false</dnp>
</player>
<player>
<name>Joakim Noah</name>
<pos>C</pos>
<start>true</start>
<min>37</min>
<fgm>9</fgm>
<fga>13</fga>
<tpm>0</tpm>
<tpa>0</tpa>
<ftm>2</ftm>
<fta>4</fta>
<oreb>4</oreb>
<dreb>8</dreb>
<reb>12</reb>
<ast>3</ast>
<stl>3</stl>
<blk>0</blk>
<to>1</to>
<pf>0</pf>
<pam>-4</pam>
<pts>20</pts>
<dnp>false</dnp>
</player>
<player>
<name>Kirk Hinrich</name>
<pos>SG</pos>
<start>true</start>
<min>32</min>
<fgm>3</fgm>
<fga>12</fga>
<tpm>2</tpm>
<tpa>5</tpa>
<ftm>6</ftm>
<fta>7</fta>
<oreb>1</oreb>
<dreb>1</dreb>
<reb>2</reb>
<ast>3</ast>
<stl>3</stl>
<blk>0</blk>
<to>0</to>
<pf>2</pf>
<pam>-5</pam>
<pts>14</pts>
<dnp>false</dnp>
</player>
<player>
<name>Tony Snell</name>
<pos>SG</pos>
<start>true</start>
<min>35</min>
<fgm>4</fgm>
<fga>8</fga>
<tpm>1</tpm>
<tpa>2</tpa>
<ftm>1</ftm>
<fta>1</fta>
<oreb>1</oreb>
<dreb>2</dreb>
<reb>3</reb>
<ast>5</ast>
<stl>1</stl>
<blk>0</blk>
<to>1</to>
<pf>5</pf>
<pam>0</pam>
<pts>10</pts>
<dnp>false</dnp>
</player>
<player>
<name>Taj Gibson</name>
<pos>PF</pos>
<start>false</start>
<min>27</min>
<fgm>5</fgm>
<fga>12</fga>
<tpm>0</tpm>
<tpa>0</tpa>
<ftm>4</ftm>
<fta>4</fta>
<oreb>4</oreb>
<dreb>4</dreb>
<reb>8</reb>
<ast>1</ast>
<stl>1</stl>
<blk>0</blk>
<to>2</to>
<pf>1</pf>
<pam>+1</pam>
<pts>14</pts>
<dnp>false</dnp>
</player>
<player>
<name>Nazr Mohammed</name>
<pos>C</pos>
<start>false</start>
<min>5</min>
<fgm>0</fgm>
<fga>0</fga>
<tpm>0</tpm>
<tpa>0</tpa>
<ftm>0</ftm>
<fta>0</fta>
<oreb>0</oreb>
<dreb>2</dreb>
<reb>2</reb>
<ast>1</ast>
<stl>0</stl>
<blk>0</blk>
<to>0</to>
<pf>0</pf>
<pam>+7</pam>
<pts>0</pts>
<dnp>false</dnp>
</player>
<player>
<name>D.J. Augustin</name>
<pos>PG</pos>
<start>false</start>
<min>29</min>
<fgm>2</fgm>
<fga>14</fga>
<tpm>1</tpm>
<tpa>8</tpa>
<ftm>5</ftm>
<fta>5</fta>
<oreb>0</oreb>
<dreb>2</dreb>
<reb>2</reb>
<ast>6</ast>
<stl>2</stl>
<blk>0</blk>
<to>2</to>
<pf>1</pf>
<pam>+12</pam>
<pts>10</pts>
<dnp>false</dnp>
</player>
<player>
<name>Jarvis Varnado</name>
<pos>PF</pos>
<start>false</start>
<min>0</min>
<fgm>0</fgm>
<fga>0</fga>
<tpm>0</tpm>
<tpa>0</tpa>
<ftm>0</ftm>
<fta>0</fta>
<oreb>0</oreb>
<dreb>0</dreb>
<reb>0</reb>
<ast>0</ast>
<stl>0</stl>
<blk>0</blk>
<to>0</to>
<pf>0</pf>
<pam>0</pam>
<pts>0</pts>
<dnp>true</dnp>
</player>
<player>
<name>Erik Murphy</name>
<pos>PF</pos>
<start>false</start>
<min>0</min>
<fgm>0</fgm>
<fga>0</fga>
<tpm>0</tpm>
<tpa>0</tpa>
<ftm>0</ftm>
<fta>0</fta>
<oreb>0</oreb>
<dreb>0</dreb>
<reb>0</reb>
<ast>0</ast>
<stl>0</stl>
<blk>0</blk>
<to>0</to>
<pf>0</pf>
<pam>0</pam>
<pts>0</pts>
<dnp>true</dnp>
</player>
<player>
<name>Tornike Shengelia</name>
<pos>SF</pos>
<start>false</start>
<min>0</min>
<fgm>0</fgm>
<fga>0</fga>
<tpm>0</tpm>
<tpa>0</tpa>
<ftm>0</ftm>
<fta>0</fta>
<oreb>0</oreb>
<dreb>0</dreb>
<reb>0</reb>
<ast>0</ast>
<stl>0</stl>
<blk>0</blk>
<to>0</to>
<pf>0</pf>
<pam>0</pam>
<pts>0</pts>
<dnp>true</dnp>
</player>
<home>false</home>
<win>true</win>
<fgm>37</fgm>
<fga>88</fga>
<tpm>8</tpm>
<tpa>24</tpa>
<ftm>25</ftm>
<fta>29</fta>
<oreb>15</oreb>
<dreb>33</dreb>
<reb>48</reb>
<ast>24</ast>
<stl>11</stl>
<blk>2</blk>
<to>12</to>
<pf>15</pf>
<pts>107</pts>
</team>
<team>
<name>Atlanta Hawks</name>
<player>
<name>Elton Brand</name>
<pos>PF</pos>
<start>true</start>
<min>42</min>
<fgm>3</fgm>
<fga>5</fga>
<tpm>0</tpm>
<tpa>0</tpa>
<ftm>1</ftm>
<fta>1</fta>
<oreb>3</oreb>
<dreb>10</dreb>
<reb>13</reb>
<ast>3</ast>
<stl>2</stl>
<blk>2</blk>
<to>3</to>
<pf>4</pf>
<pam>+6</pam>
<pts>7</pts>
<dnp>false</dnp>
</player>
<player>
<name>DeMarre Carroll</name>
<pos>SF</pos>
<start>true</start>
<min>34</min>
<fgm>4</fgm>
<fga>12</fga>
<tpm>2</tpm>
<tpa>5</tpa>
<ftm>3</ftm>
<fta>3</fta>
<oreb>2</oreb>
<dreb>2</dreb>
<reb>4</reb>
<ast>1</ast>
<stl>1</stl>
<blk>0</blk>
<to>2</to>
<pf>5</pf>
<pam>-6</pam>
<pts>13</pts>
<dnp>false</dnp>
</player>
<player>
<name>Shelvin Mack</name>
<pos>PG</pos>
<start>true</start>
<min>27</min>
<fgm>8</fgm>
<fga>14</fga>
<tpm>1</tpm>
<tpa>5</tpa>
<ftm>0</ftm>
<fta>0</fta>
<oreb>1</oreb>
<dreb>3</dreb>
<reb>4</reb>
<ast>3</ast>
<stl>0</stl>
<blk>0</blk>
<to>0</to>
<pf>2</pf>
<pam>-4</pam>
<pts>17</pts>
<dnp>false</dnp>
</player>
<player>
<name>Jeff Teague</name>
<pos>PG</pos>
<start>true</start>
<min>35</min>
<fgm>10</fgm>
<fga>20</fga>
<tpm>3</tpm>
<tpa>4</tpa>
<ftm>3</ftm>
<fta>4</fta>
<oreb>0</oreb>
<dreb>2</dreb>
<reb>2</reb>
<ast>7</ast>
<stl>0</stl>
<blk>0</blk>
<to>4</to>
<pf>3</pf>
<pam>+5</pam>
<pts>26</pts>
<dnp>false</dnp>
</player>
<player>
<name>Kyle Korver</name>
<pos>SG</pos>
<start>true</start>
<min>39</min>
<fgm>4</fgm>
<fga>10</fga>
<tpm>4</tpm>
<tpa>9</tpa>
<ftm>4</ftm>
<fta>4</fta>
<oreb>0</oreb>
<dreb>7</dreb>
<reb>7</reb>
<ast>3</ast>
<stl>2</stl>
<blk>0</blk>
<to>2</to>
<pf>4</pf>
<pam>+5</pam>
<pts>16</pts>
<dnp>false</dnp>
</player>
<player>
<name>Mike Scott</name>
<pos>PF</pos>
<start>false</start>
<min>33</min>
<fgm>5</fgm>
<fga>12</fga>
<tpm>2</tpm>
<tpa>5</tpa>
<ftm>0</ftm>
<fta>0</fta>
<oreb>2</oreb>
<dreb>5</dreb>
<reb>7</reb>
<ast>3</ast>
<stl>1</stl>
<blk>0</blk>
<to>4</to>
<pf>3</pf>
<pam>-9</pam>
<pts>12</pts>
<dnp>false</dnp>
</player>
<player>
<name>Cartier Martin</name>
<pos>PF</pos>
<start>false</start>
<min>2</min>
<fgm>0</fgm>
<fga>0</fga>
<tpm>0</tpm>
<tpa>0</tpa>
<ftm>0</ftm>
<fta>0</fta>
<oreb>0</oreb>
<dreb>0</dreb>
<reb>0</reb>
<ast>0</ast>
<stl>0</stl>
<blk>0</blk>
<to>0</to>
<pf>0</pf>
<pam>-8</pam>
<pts>0</pts>
<dnp>false</dnp>
</player>
<player>
<name>Dexter Pittman</name>
<pos>C</pos>
<start>false</start>
<min>2</min>
<fgm>0</fgm>
<fga>1</fga>
<tpm>0</tpm>
<tpa>0</tpa>
<ftm>0</ftm>
<fta>2</fta>
<oreb>3</oreb>
<dreb>0</dreb>
<reb>3</reb>
<ast>0</ast>
<stl>0</stl>
<blk>0</blk>
<to>0</to>
<pf>0</pf>
<pam>-2</pam>
<pts>0</pts>
<dnp>false</dnp>
</player>
<player>
<name>Louis Williams</name>
<pos>SG</pos>
<start>false</start>
<min>26</min>
<fgm>4</fgm>
<fga>10</fga>
<tpm>2</tpm>
<tpa>5</tpa>
<ftm>2</ftm>
<fta>2</fta>
<oreb>0</oreb>
<dreb>2</dreb>
<reb>2</reb>
<ast>1</ast>
<stl>1</stl>
<blk>0</blk>
<to>1</to>
<pf>1</pf>
<pam>-7</pam>
<pts>12</pts>
<dnp>false</dnp>
</player>
<player>
<name>Gustavo Ayon</name>
<pos>PF</pos>
<start>false</start>
<min>0</min>
<fgm>0</fgm>
<fga>0</fga>
<tpm>0</tpm>
<tpa>0</tpa>
<ftm>0</ftm>
<fta>0</fta>
<oreb>0</oreb>
<dreb>0</dreb>
<reb>0</reb>
<ast>0</ast>
<stl>0</stl>
<blk>0</blk>
<to>0</to>
<pf>0</pf>
<pam>0</pam>
<pts>0</pts>
<dnp>true</dnp>
</player>
<player>
<name>Paul Millsap</name>
<pos>PF</pos>
<start>false</start>
<min>0</min>
<fgm>0</fgm>
<fga>0</fga>
<tpm>0</tpm>
<tpa>0</tpa>
<ftm>0</ftm>
<fta>0</fta>
<oreb>0</oreb>
<dreb>0</dreb>
<reb>0</reb>
<ast>0</ast>
<stl>0</stl>
<blk>0</blk>
<to>0</to>
<pf>0</pf>
<pam>0</pam>
<pts>0</pts>
<dnp>true</dnp>
</player>
<home>true</home>
<win>false</win>
<fgm>38</fgm>
<fga>84</fga>
<tpm>14</tpm>
<tpa>33</tpa>
<ftm>13</ftm>
<fta>16</fta>
<oreb>11</oreb>
<dreb>31</dreb>
<reb>42</reb>
<ast>21</ast>
<stl>7</stl>
<blk>2</blk>
<to>16</to>
<pf>22</pf>
<pts>103</pts>
</team>
</game>